{"stats":{"minecraft:used":{"minecraft:sticky_piston":1,"minecraft:packed_ice":106,"minecraft:lava_bucket":1,"minecraft:cyan_shulker_box":1,"minecraft:command_block":5,"minecraft:powered_rail":391,"minecraft:redstone":83,"minecraft:armor_stand":2,"minecraft:spruce_slab":2,"minecraft:brown_wool":56,"minecraft:sculk":88,"minecraft:black_glazed_terracotta":10,"minecraft:redstone_block":3,"minecraft:barrel":3,"minecraft:polished_blackstone_bricks":1,"minecraft:torch":17,"minecraft:stripped_mangrove_wood":151,"minecraft:repeater":8,"minecraft:golden_carrot":1,"minecraft:comparator":5,"minecraft:written_book":21,"minecraft:deepslate_coal_ore":6,"minecraft:chain_command_block":1,"minecraft:note_block":2,"minecraft:brown_glazed_terracotta":1,"minecraft:cobbled_deepslate":5,"minecraft:powder_snow_bucket":2,"minecraft:observer":42,"minecraft:purple_wool":72,"minecraft:obsidian":1},"minecraft:dropped":{"minecraft:compass":1,"minecraft:iron_nugget":1,"minecraft:lingering_potion":1,"minecraft:composter":1},"minecraft:picked_up":{"minecraft:wooden_axe":1,"minecraft:lingering_potion":1,"minecraft:basalt":5,"minecraft:repeater":1,"minecraft:pumpkin":2,"minecraft:glow_ink_sac":10,"minecraft:sweet_berries":6,"minecraft:filled_map":1,"minecraft:amethyst_shard":5,"minecraft:light":1,"minecraft:redstone":2,"minecraft:cyan_shulker_box":1,"minecraft:spider_eye":2,"minecraft:twisting_vines":1,"minecraft:compass":1,"minecraft:cactus":2,"minecraft:sugar":2,"minecraft:slime_ball":2,"minecraft:tropical_fish":4,"minecraft:carved_pumpkin":64,"minecraft:bone_meal":1,"minecraft:written_book":34,"minecraft:iron_nugget":64,"minecraft:melon_slice":5,"minecraft:glow_berries":5,"minecraft:egg":1},"minecraft:custom":{"minecraft:time_since_rest":496249,"minecraft:inspect_dropper":95,"minecraft:sprint_one_cm":12636,"minecraft:damage_taken":230,"minecraft:walk_one_cm":361315,"minecraft:drop":4,"minecraft:inspect_hopper":35,"minecraft:minecart_one_cm":15092,"minecraft:damage_dealt":20,"minecraft:swim_one_cm":296,"minecraft:tune_noteblock":2,"minecraft:fly_one_cm":1909120,"minecraft:open_barrel":26,"minecraft:open_chest":3,"minecraft:crouch_one_cm":3266,"minecraft:play_time":496249,"minecraft:open_shulker_box":30,"minecraft:sneak_time":11212,"minecraft:walk_under_water_one_cm":22483,"minecraft:jump":178,"minecraft:leave_game":1,"minecraft:time_since_death":496249,"minecraft:walk_on_water_one_cm":24567,"minecraft:climb_one_cm":440,"minecraft:total_world_time":496249,"minecraft:fall_one_cm":793,"minecraft:inspect_dispenser":1}},"DataVersion":3465}